osint_tools/__init__.py
osint_tools/db/__init__.py
osint_tools/db/mongo_db/__init__.py
osint_tools/db/mongo_db/manager.py
osint_tools/four_chan/__init__.py
osint_tools/four_chan/api/__init__.py
osint_tools/four_chan/api/four_chan.py
osint_tools/four_chan/api/four_chan_async.py
osint_tools/four_chan/schemas/__init__.py
osint_tools/four_chan/schemas/config.py
osint_tools/four_chan/schemas/schema.py
osint_tools/logger.json
osint_tools/logs.py
osint_tools/rss/__init__.py
osint_tools/rss/schemas/__init__.py
osint_tools/rss/schemas/config.py
osint_tools/rss/schemas/fields.py
osint_tools/rss/schemas/schema.py
osint_tools/settings.py
osint_tools-0.4.1.dist-info/METADATA
osint_tools-0.4.1.dist-info/WHEEL
osint_tools-0.4.1.dist-info/RECORD
