Metadata-Version: 2.1
Name: osint_tools
Version: 0.4.1
Summary: 
Author: Alexander Slessor
Author-email: alexjslessor@gmail.com.com
Requires-Python: >=3.8,<4.0
Classifier: Programming Language :: Python :: 3
Classifier: Programming Language :: Python :: 3.8
Classifier: Programming Language :: Python :: 3.9
Classifier: Programming Language :: Python :: 3.10
Classifier: Programming Language :: Python :: 3.11
Classifier: Programming Language :: Python :: 3.12
Requires-Dist: chardet (==4.0.0)
Requires-Dist: feedparser (>=6.0.8,<7.0.0)
Requires-Dist: motor (>=3.3.1,<4.0.0)
Requires-Dist: pydantic (==1.10.13)
Requires-Dist: python-jose (>=3.3.0,<4.0.0)
